{
  "format_version": "1.10.0",
  "minecraft:attachable": {
    "description": {
      "identifier": "miraculous:aquabella_chestplate",
      "item": { "miraculous:aquabella_chestplate": "query.owner_identifier == 'minecraft:player'" },
      "materials": {
        "default": "armor",
        "enchanted": "armor_enchanted"
      },
      "textures": {
        "default": "textures/miraculous/ladybug_miraculous/scarabella/aqua/aquabella_chestplate",
        "enchanted": "textures/misc/enchanted_item_glint"
      },
      "geometry": {
        "default": "geometry.aquabella_chestplate"
      },
      "scripts": {
        "parent_setup": "variable.helmet_layer_visible = 0.0;"
      },
      "render_controllers": [ "controller.render.armor" ]
    }
  }
}
